modules/lookup_table.v
module lookup_table (
    input  wire [2:0] vel_index,
    output reg  [31:0] T_value
);

    always @(*) begin
        case (vel_index)
            3'd0: T_value = 32'd125000;  // 400 Hz
            3'd1: T_value = 32'd62500;   // 800 Hz
            3'd2: T_value = 32'd31250;   // 1.6 kHz
            3'd3: T_value = 32'd20833;   // 2.4 kHz
            3'd4: T_value = 32'd15625;   // 3.2 kHz
            3'd5: T_value = 32'd12500;   // 4.0 kHz
            3'd6: T_value = 32'd8929;    // 5.6 kHz
            3'd7: T_value = 32'd7813;    // 6.4 kHz
        endcase
    end

endmodule

modules/bldc_registers.v
module bldc_registers (
    input  wire        clk,
    input  wire        rst,
    input  wire        write,
    input  wire        read,
    input  wire [0:0]  addr,       // 0: CONFIG, 1: OUT
    input  wire [31:0] data_in,
    output reg  [31:0] data_out,
    output wire [7:0]  vel,
    output wire [7:0]  duty,
    output wire        en,
    input  wire [2:0]  phase_state // desde FSM externa
);

    // -----------------------------
    // Registros internos
    // -----------------------------
    reg [7:0] vel_reg;
    reg [7:0] duty_reg;
    reg       en_reg;

    // -----------------------------
    // Escritura sincrónica
    // -----------------------------
    always @(posedge clk or posedge rst) begin
        if (rst) begin
            vel_reg  <= 8'd0;
            duty_reg <= 8'd0;
            en_reg   <= 1'b0;
        end else if (write && addr == 1'b0) begin // CONFIG
            vel_reg  <= data_in[31:24];
            duty_reg <= data_in[23:16];
            en_reg   <= data_in[15];
        end
    end

    // -----------------------------
    // Lectura sincrónica (registrada)
    // -----------------------------
    always @(posedge clk or posedge rst) begin
        if (rst) begin
            data_out <= 32'd0;
        end else if (read && addr == 1'b1) begin // OUT
            data_out <= {
                vel_reg,         // [31:24]
                duty_reg,        // [23:16]
                en_reg,          // [15]
                1'b0,            // padding
                phase_state,     // [13:11]
                11'd0            // padding
            };
        end
    end

    // -----------------------------
    // Conexiones de salida
    // -----------------------------
    assign vel  = vel_reg;
    assign duty = duty_reg;
    assign en   = en_reg;

endmodule

testbenchs/tb_bldc_registers.v
`timescale 1ns/1ps
module tb_bldc_registers_lookup_combo;

    reg         clk, rst;
    reg         write, read;
    reg  [0:0]  addr;
    reg  [31:0] data_in;
    wire [31:0] data_out;
    wire [7:0]  vel, duty;
    wire        en;
    reg  [2:0]  phase_state;
    wire [31:0] T;

    // Clock 50 MHz
    always #10 clk = ~clk;

    // Instancias
    bldc_registers regs (
        .clk(clk),
        .rst(rst),
        .write(write),
        .read(read),
        .addr(addr),
        .data_in(data_in),
        .data_out(data_out),
        .vel(vel),
        .duty(duty),
        .en(en),
        .phase_state(phase_state)
    );

    lookup_table lut (
        .vel_index(vel[2:0]),
        .T_value(T)
    );

    // Variables auxiliares
    integer v, d;
    reg [7:0] vel_fixed = 8'd3;
    reg       en_fixed  = 1'b1;

    initial begin
        $dumpfile("tb_bldc_registers.vcd");
        $dumpvars(0, tb_bldc_registers_lookup_combo);

        clk = 0;
        rst = 1;
        write = 0;
        read = 0;
        addr = 0;
        data_in = 32'd0;
        phase_state = 3'b011;

        #40 rst = 0;

        // PWM test: velocidad fija, duty variable
        for (d = 0; d < 4; d = d + 1) begin
            #40;
            addr = 0;
            data_in = 32'd0;
            data_in[31:24] = vel_fixed;
            data_in[23:16] = d * 64;
            data_in[15]    = en_fixed;
            write = 1;
            #20 write = 0;

            addr = 1;
            read = 1;
            #20 read = 0;

            $display("PWM -> vel = %0d, duty = %0d, T = %0d", vel, duty, T);
            $display("data_out = %h | vel = %0d, duty = %0d, en = %b",
                      data_out, data_out[31:24], data_out[23:16], data_out[15]);
        end

        // FSM test: duty fijo, velocidad variable
        for (v = 0; v < 8; v = v + 1) begin
            #40;
            addr = 0;
            data_in = 32'd0;
            data_in[31:24] = v[7:0];
            data_in[23:16] = 8'd128;
            data_in[15]    = en_fixed;
            write = 1;
            #20 write = 0;

            addr = 1;
            read = 1;
            #20 read = 0;

            $display("FSM -> vel = %0d, duty = %0d, T = %0d", vel, duty, T);
            $display("data_out = %h | vel = %0d, duty = %0d, en = %b",
                      data_out, data_out[31:24], data_out[23:16], data_out[15]);
        end

        #100 $finish;
    end

endmodule

tb_bldc_registers.vcd
$date
	Mon Jul 14 13:23:36 2025
$end
$version
	Icarus Verilog
$end
$timescale
	1ps
$end
$scope module tb_bldc_registers_lookup_combo $end
$var wire 8 ! vel [7:0] $end
$var wire 1 " en $end
$var wire 8 # duty [7:0] $end
$var wire 32 $ data_out [31:0] $end
$var wire 32 % T [31:0] $end
$var reg 1 & addr $end
$var reg 1 ' clk $end
$var reg 32 ( data_in [31:0] $end
$var reg 1 ) en_fixed $end
$var reg 3 * phase_state [2:0] $end
$var reg 1 + read $end
$var reg 1 , rst $end
$var reg 8 - vel_fixed [7:0] $end
$var reg 1 . write $end
$var integer 32 / d [31:0] $end
$var integer 32 0 v [31:0] $end
$scope module lut $end
$var wire 3 1 vel_index [2:0] $end
$var reg 32 2 T_value [31:0] $end
$upscope $end
$scope module regs $end
$var wire 1 & addr $end
$var wire 1 ' clk $end
$var wire 32 3 data_in [31:0] $end
$var wire 8 4 duty [7:0] $end
$var wire 1 " en $end
$var wire 3 5 phase_state [2:0] $end
$var wire 1 + read $end
$var wire 1 , rst $end
$var wire 1 . write $end
$var wire 8 6 vel [7:0] $end
$var reg 32 7 data_out [31:0] $end
$var reg 8 8 duty_reg [7:0] $end
$var reg 1 9 en_reg $end
$var reg 8 : vel_reg [7:0] $end
$upscope $end
$upscope $end
$enddefinitions $end
#0
$dumpvars
b0 :
09
b0 8
b0 7
b0 6
b11 5
b0 4
b0 3
b11110100001001000 2
b0 1
bx 0
bx /
0.
b11 -
1,
0+
b11 *
1)
b0 (
0'
0&
b11110100001001000 %
b0 $
b0 #
0"
b0 !
$end
#10000
1'
#20000
0'
#30000
1'
#40000
0'
b0 /
0,
#50000
1'
#60000
0'
#70000
1'
#80000
0'
1.
b11000000001000000000000000 (
b11000000001000000000000000 3
#90000
b101000101100001 %
b101000101100001 2
b11 1
1"
19
b11 !
b11 6
b11 :
1'
#100000
0'
1+
1&
0.
#110000
b11000000001001100000000000 $
b11000000001001100000000000 7
1'
#120000
0'
b1 /
0+
#130000
1'
#140000
0'
#150000
1'
#160000
0'
1.
b11010000001000000000000000 (
b11010000001000000000000000 3
0&
#170000
b1000000 #
b1000000 4
b1000000 8
1'
#180000
0'
1+
1&
0.
#190000
b11010000001001100000000000 $
b11010000001001100000000000 7
1'
#200000
0'
b10 /
0+
#210000
1'
#220000
0'
#230000
1'
#240000
0'
1.
b11100000001000000000000000 (
b11100000001000000000000000 3
0&
#250000
b10000000 #
b10000000 4
b10000000 8
1'
#260000
0'
1+
1&
0.
#270000
b11100000001001100000000000 $
b11100000001001100000000000 7
1'
#280000
0'
b11 /
0+
#290000
1'
#300000
0'
#310000
1'
#320000
0'
1.
b11110000001000000000000000 (
b11110000001000000000000000 3
0&
#330000
b11000000 #
b11000000 4
b11000000 8
1'
#340000
0'
1+
1&
0.
#350000
b11110000001001100000000000 $
b11110000001001100000000000 7
1'
#360000
0'
b0 0
b100 /
0+
#370000
1'
#380000
0'
#390000
1'
#400000
0'
1.
b100000001000000000000000 (
b100000001000000000000000 3
0&
#410000
b11110100001001000 %
b11110100001001000 2
b0 1
b10000000 #
b10000000 4
b10000000 8
b0 !
b0 6
b0 :
1'
#420000
0'
1+
1&
0.
#430000
b100000001001100000000000 $
b100000001001100000000000 7
1'
#440000
0'
b1 0
0+
#450000
1'
#460000
0'
#470000
1'
#480000
0'
1.
b1100000001000000000000000 (
b1100000001000000000000000 3
0&
#490000
b1111010000100100 %
b1111010000100100 2
b1 1
b1 !
b1 6
b1 :
1'
#500000
0'
1+
1&
0.
#510000
b1100000001001100000000000 $
b1100000001001100000000000 7
1'
#520000
0'
b10 0
0+
#530000
1'
#540000
0'
#550000
1'
#560000
0'
1.
b10100000001000000000000000 (
b10100000001000000000000000 3
0&
#570000
b111101000010010 %
b111101000010010 2
b10 1
b10 !
b10 6
b10 :
1'
#580000
0'
1+
1&
0.
#590000
b10100000001001100000000000 $
b10100000001001100000000000 7
1'
#600000
0'
b11 0
0+
#610000
1'
#620000
0'
#630000
1'
#640000
0'
1.
b11100000001000000000000000 (
b11100000001000000000000000 3
0&
#650000
b101000101100001 %
b101000101100001 2
b11 1
b11 !
b11 6
b11 :
1'
#660000
0'
1+
1&
0.
#670000
b11100000001001100000000000 $
b11100000001001100000000000 7
1'
#680000
0'
b100 0
0+
#690000
1'
#700000
0'
#710000
1'
#720000
0'
1.
b100100000001000000000000000 (
b100100000001000000000000000 3
0&
#730000
b11110100001001 %
b11110100001001 2
b100 1
b100 !
b100 6
b100 :
1'
#740000
0'
1+
1&
0.
#750000
b100100000001001100000000000 $
b100100000001001100000000000 7
1'
#760000
0'
b101 0
0+
#770000
1'
#780000
0'
#790000
1'
#800000
0'
1.
b101100000001000000000000000 (
b101100000001000000000000000 3
0&
#810000
b11000011010100 %
b11000011010100 2
b101 1
b101 !
b101 6
b101 :
1'
#820000
0'
1+
1&
0.
#830000
b101100000001001100000000000 $
b101100000001001100000000000 7
1'
#840000
0'
b110 0
0+
#850000
1'
#860000
0'
#870000
1'
#880000
0'
1.
b110100000001000000000000000 (
b110100000001000000000000000 3
0&
#890000
b10001011100001 %
b10001011100001 2
b110 1
b110 !
b110 6
b110 :
1'
#900000
0'
1+
1&
0.
#910000
b110100000001001100000000000 $
b110100000001001100000000000 7
1'
#920000
0'
b111 0
0+
#930000
1'
#940000
0'
#950000
1'
#960000
0'
1.
b111100000001000000000000000 (
b111100000001000000000000000 3
0&
#970000
b1111010000101 %
b1111010000101 2
b111 1
b111 !
b111 6
b111 :
1'
#980000
0'
1+
1&
0.
#990000
b111100000001001100000000000 $
b111100000001001100000000000 7
1'
#1000000
0'
b1000 0
0+
