modules/pwm_generator.v
module pwm_generator (
    input  wire        clk,
    input  wire        rst,
    input  wire        en,
    input  wire [7:0]  duty,     // Duty cycle 0-255
    output reg         pwm_out
);

    // Frecuencia fija - PWM funciona a 1MHz
    localparam integer PWM_PERIOD = 50;

    reg [6:0] counter;
    wire [6:0] threshold;       // Umbral calculado con duty
    assign threshold = (PWM_PERIOD * duty) >> 8;

    always @(posedge clk or posedge rst) begin
        if (rst) begin
            counter <= 12'd0;
            pwm_out <= 1'b0;
        end else if (en) begin
            // Contador principal
            if (counter >= PWM_PERIOD - 1)
                counter <= 12'd0;
            else
                counter <= counter + 1;

            // Comparación para activar salida PWM
            pwm_out <= (counter < threshold);
        end else begin
            counter <= 12'd0;
            pwm_out <= 1'b0;
        end
    end
endmodule

modules/variable_frequency_wave_generator.v
module variable_frequency_wave_generator (
    // Inputs
    input wire         clk,
    input wire         rst, // Active-low asynchronous reset
    input wire [31:0]  T_value,

    // Output
    output reg [2:0]   output_val
);

    // Internal registers for the two counters
    reg [31:0] main_counter;   // This counter increments on every clock edge up to T_value
    reg [5:0]  state_counter;  // This counter increments from 0-47 when the main_counter wraps

    // --- Sequential Logic Block ---
    // This block describes the behavior of the counters on each clock edge.
    always @(posedge clk or negedge rst) begin
        if (!rst) begin
            // Reset counters to zero if rst is asserted (low)
            main_counter  <= 32'd0;
            state_counter <= 6'd0;
        end
        else begin
            // Check if the main counter has reached its target value
            if (main_counter >= T_value) begin
                main_counter <= 32'd0; // Reset the main counter

                // Increment the state counter, wrapping from 47 back to 0
                if (state_counter == 6'd47) begin
                    state_counter <= 6'd0;
                end
                else begin
                    state_counter <= state_counter + 1;
                end
            end
            else begin
                // If the target is not reached, just increment the main counter
                main_counter <= main_counter + 1;
            end
        end
    end

    // --- Combinational Logic Block ---
    // This block determines the output value based on the current state of the state_counter.
    // It uses a priority-encoded if-else structure, which is efficient for synthesis.
    always @(*) begin
        if (state_counter <= 7) begin
            output_val = 3'b110;
        end
        else if (state_counter <= 15) begin
            output_val = 3'b100;
        end
        else if (state_counter <= 23) begin
            output_val = 3'b101;
        end
        else if (state_counter <= 31) begin
            output_val = 3'b001;
        end
        else if (state_counter <= 39) begin
            output_val = 3'b011;
        end
        else begin // Covers states from 40 to 47
            output_val = 3'b010;
        end
    end

endmodule

lookup_table.v
module lookup_table (
    input  wire [7:0] vel_onehot,
    output reg  [31:0] T_value
);

    always @(*) begin
        case (vel_onehot)
            8'b00000001: T_value = 32'd125000; // velocidad 0 → 400 Hz
            8'b00000010: T_value = 32'd62500;  // velocidad 1 → 800 Hz
            8'b00000100: T_value = 32'd31250;  // velocidad 2 → 1.6 kHz
            8'b00001000: T_value = 32'd20833;  // velocidad 3 → 2.4 kHz
            8'b00010000: T_value = 32'd15625;  // velocidad 4 → 3.2 kHz
            8'b00100000: T_value = 32'd12500;  // velocidad 5 → 4.0 kHz
            8'b01000000: T_value = 32'd8929;   // velocidad 6 → 5.6 kHz
            8'b10000000: T_value = 32'd7813;   // velocidad 7 → 6.4 kHz
            default:     T_value = 32'd0;       // default o error
        endcase
    end

endmodule

modules/bldc_registers.v
module bldc_registers (
    input  wire        clk,
    input  wire        rst,
    input  wire        write,
    input  wire        read,
    input  wire [31:0]  addr,       // 0: CONFIG, 1: OUT
    input  wire [31:0] data_in,
    output reg  [31:0] data_out,
    output wire [7:0]  vel,
    output wire [7:0]  duty,
    output wire        en,
    input  wire [2:0]  phase_state // desde FSM externa
);

    // -----------------------------
    // Registros internos
    // -----------------------------
    reg [7:0] vel_reg;
    reg [7:0] duty_reg;
    reg       en_reg;

    // -----------------------------
    // Escritura sincrónica
    // -----------------------------
    always @(posedge clk or posedge rst) begin
        if (rst) begin
            vel_reg  <= 8'd0;
            duty_reg <= 8'd0;
            en_reg   <= 1'b0;
        end else if (write && addr == 1'b0) begin // CONFIG
            vel_reg  <= data_in[31:24];
            duty_reg <= data_in[23:16];
            en_reg   <= data_in[15];
        end
    end

    // -----------------------------
    // Lectura sincrónica (registrada)
    // -----------------------------
    always @(posedge clk or posedge rst) begin
        if (rst) begin
            data_out <= 32'd0;
        end else if (read && addr == 1'b1) begin // OUT
            data_out <= {
                vel_reg,         // [31:24]
                duty_reg,        // [23:16]
                en_reg,          // [15]
                1'b0,            // padding
                phase_state,     // [13:11]
                11'd0            // padding
            };
        end
    end

    // -----------------------------
    // Conexiones de salida
    // -----------------------------
    assign vel  = vel_reg;
    assign duty = duty_reg;
    assign en   = en_reg;

endmodule

modules/bldc_controller.v
module bldc_controller (
    input  wire        clk,
    input  wire        rst,
    input  wire        write,
    input  wire        read,
    input  wire [31:0]  addr,
    input  wire [31:0] data_in,
    output wire [31:0] data_out,
    output wire [2:0]  output_combined
);

    // Internal signals
    wire [7:0] vel;
    wire [7:0] duty;
    wire [2:0] phase_state; // From FSM (external input for bldc_registers)
    wire [31:0] T_value;
    wire pwm_out;
    wire [2:0] output_val;
    wire rst_n;


    // --- Phase State (placeholder for integration with external FSM) ---
    assign phase_state = output_val; // Connect output of wave gen to phase state input

    assign rst_n = ~ rst;

    // -----------------------------
    // Module Instantiations
    // -----------------------------

    bldc_registers u_registers (
        .clk(clk),
        .rst(rst),
        .write(write),
        .read(read),
        .addr(addr),
        .data_in(data_in),
        .data_out(data_out),
        .vel(vel),
        .duty(duty),
        .en(en),
        .phase_state(phase_state)
    );

    lookup_table u_lookup (
        .vel_onehot(vel),
        .T_value(T_value)
    );

    variable_frequency_wave_generator u_wavegen (
        .clk(clk & T_value!=8'd0),
        .rst(rst_n),
        .T_value(T_value),
        .output_val(output_val)
    );

    pwm_generator u_pwm (
        .clk(clk),
        .rst(rst),
        .en(en),
        .duty(duty),
        .pwm_out(pwm_out)
    );

    assign output_combined = {3 {pwm_out}} & phase_state & {3{en}} & {3{T_value!=8'b0}};

endmodule

testbenchs/tb_bldc_controller.v
`timescale 1ns / 1ns

module tb_bldc_controller;

    reg clk, rst, write, read;
    reg [31:0] addr;
    reg [31:0] data_in;
    wire [31:0] data_out;
    wire [2:0] output_combined;

    // Instantiate the DUT
    bldc_controller uut (
        .clk(clk),
        .rst(rst),
        .write(write),
        .read(read),
        .addr(addr),
        .data_in(data_in),
        .data_out(data_out),
        .output_combined(output_combined)
    );

    // Clock generation
    initial clk = 0;
    always #10 clk = ~clk;  // 50 MHz clock

    initial begin
        $dumpfile("vcd_results/tb_bldc_controller.vcd");
        $dumpvars(0, tb_bldc_controller);
        // Initialize
        rst = 0;
        write = 0;
        read = 0;
        addr = 32'd0;
        data_in = 0;

        // Hold reset
        #30;
        rst = 1;
        #30;
        rst = 0;
        #30

        // Write to CONFIG register: vel=6, duty=128 (50%), en=1
        addr = 32'd0;
        data_in = {8'b00001000, 8'd128, 1'b1, 15'd0}; // vel=2 (1.6 kHz), duty=50%
        write = 1;
        #30;
        write = 0;

        // Read from OUT register
        #30;
        addr = 32'd1;
        read = 1;
        #30;
        read = 0;

        // Let simulation run
        #250000;

        // Write to CONFIG register: vel=6, duty=128 (50%), en=0
        addr = 32'd0;
        data_in = {8'b01000000, 8'd128, 1'b0, 15'd0}; // vel=2 (1.6 kHz), duty=50%
        write = 1;
        #30;
        write = 0;

        // Let simulation run
        #50000;

        // Write to CONFIG register: vel=6, duty=200 (78%), en=1
        addr = 32'd0;
        data_in = {8'b10000000, 8'd200, 1'b1, 15'd0}; // vel=2 (1.6 kHz), duty=50%
        write = 1;
        #30;
        write = 0;

        #250000;
        // Read from OUT register
        #30;
        addr = 32'd1;
        read = 1;
        #30;
        read = 0;

        // Write to CONFIG register: vel=NOT VALID, duty=128 (50%), en=1
        addr = 32'd0;
        data_in = {8'b10100000, 8'd128, 1'b1, 15'd0}; // vel=2 (1.6 kHz), duty=50%
        write = 1;
        #30;
        write = 0;

        #25000;
        // Read from OUT register
        #30;
        addr = 32'd1;
        read = 1;
        #30;
        read = 0;

        #25000;

        $finish;
    end

endmodule

vcd_results/tb_bldc_controller.vcd
$date
	Mon Jul 21 16:33:33 2025
$end
$version
	Icarus Verilog
$end
$timescale
	1ns
$end
$scope module tb_bldc_controller $end
$var wire 3 ! output_combined [2:0] $end
$var wire 32 " data_out [31:0] $end
$var reg 32 # addr [31:0] $end
$var reg 1 $ clk $end
$var reg 32 % data_in [31:0] $end
$var reg 1 & read $end
$var reg 1 ' rst $end
$var reg 1 ( write $end
$scope module uut $end
$var wire 32 ) addr [31:0] $end
$var wire 1 $ clk $end
$var wire 32 * data_in [31:0] $end
$var wire 3 + output_combined [2:0] $end
$var wire 3 , phase_state [2:0] $end
$var wire 1 & read $end
$var wire 1 ' rst $end
$var wire 1 - rst_n $end
$var wire 1 ( write $end
$var wire 8 . vel [7:0] $end
$var wire 1 / pwm_out $end
$var wire 3 0 output_val [2:0] $end
$var wire 1 1 en $end
$var wire 8 2 duty [7:0] $end
$var wire 32 3 data_out [31:0] $end
$var wire 32 4 T_value [31:0] $end
$scope module u_lookup $end
$var wire 8 5 vel_onehot [7:0] $end
$var reg 32 6 T_value [31:0] $end
$upscope $end
$scope module u_pwm $end
$var wire 1 $ clk $end
$var wire 1 ' rst $end
$var wire 7 7 threshold [6:0] $end
$var wire 1 1 en $end
$var wire 8 8 duty [7:0] $end
$var parameter 32 9 PWM_PERIOD $end
$var reg 7 : counter [6:0] $end
$var reg 1 / pwm_out $end
$upscope $end
$scope module u_registers $end
$var wire 32 ; addr [31:0] $end
$var wire 1 $ clk $end
$var wire 32 < data_in [31:0] $end
$var wire 3 = phase_state [2:0] $end
$var wire 1 & read $end
$var wire 1 ' rst $end
$var wire 8 > vel [7:0] $end
$var wire 1 ( write $end
$var wire 1 1 en $end
$var wire 8 ? duty [7:0] $end
$var reg 32 @ data_out [31:0] $end
$var reg 8 A duty_reg [7:0] $end
$var reg 1 1 en_reg $end
$var reg 8 B vel_reg [7:0] $end
$upscope $end
$scope module u_wavegen $end
$var wire 32 C T_value [31:0] $end
$var wire 1 D clk $end
$var wire 1 - rst $end
$var reg 32 E main_counter [31:0] $end
$var reg 3 F output_val [2:0] $end
$var reg 6 G state_counter [5:0] $end
$upscope $end
$upscope $end
$upscope $end
$enddefinitions $end
$comment Show the parameter values. $end
$dumpall
b110010 9
$end
#0
$dumpvars
bx G
bx F
bx E
0D
bx C
bx B
bx A
bx @
bx ?
bx >
bx =
b0 <
b0 ;
bx :
bx 8
bx 7
bx 6
bx 5
bx 4
bx 3
bx 2
x1
bx 0
x/
bx .
1-
bx ,
bx +
b0 *
b0 )
0(
0'
0&
b0 %
0$
b0 #
bx "
bx !
$end
#10
b0 !
b0 +
0/
b0 :
xD
1$
#20
0D
0$
#30
b0 7
b110 ,
b110 =
b110 0
b110 F
b0 4
b0 6
b0 C
b0 G
b0 E
b0 "
b0 3
b0 @
01
b0 2
b0 8
b0 ?
b0 A
b0 .
b0 5
b0 >
b0 B
0D
0-
1$
1'
#40
0$
#50
1$
#60
1-
0$
0'
#70
1$
#80
0$
#90
b1 E
b11001 7
1D
b110110001 4
b110110001 6
b110110001 C
11
b10000000 2
b10000000 8
b10000000 ?
b10000000 A
b1000 .
b1000 5
b1000 >
b1000 B
1$
1(
b1000100000001000000000000000 %
b1000100000001000000000000000 *
b1000100000001000000000000000 <
#100
0D
0$
#110
b110 !
b110 +
b10 E
1/
b1 :
1D
1$
#120
0D
0$
0(
#130
b11 E
b10 :
1D
1$
#140
0D
0$
#150
b100 E
b11 :
b1000100000001011000000000000 "
b1000100000001011000000000000 3
b1000100000001011000000000000 @
1D
1$
1&
b1 #
b1 )
b1 ;
#160
0D
0$
#170
b101 E
b100 :
1D
1$
#180
0D
0$
0&
#190
b110 E
b101 :
1D
1$
#200
0D
0$
#210
b111 E
b110 :
1D
1$
#220
0D
0$
#230
b1000 E
b111 :
1D
1$
#240
0D
0$
#250
b1001 E
b1000 :
1D
1$
#260
0D
0$
#270
b1010 E
b1001 :
1D
1$
#280
0D
0$
#290
b1011 E
b1010 :
1D
1$
#300
0D
0$
#310
b1100 E
b1011 :
1D
1$
#320
0D
0$
#330
b1101 E
b1100 :
1D
1$
#340
0D
0$
#350
b1110 E
b1101 :
1D
1$
#360
0D
0$
#370
b1111 E
b1110 :
1D
1$
#380
0D
0$
#390
b10000 E
b1111 :
1D
1$
#400
0D
0$
#410
b10001 E
b10000 :
1D
1$
#420
0D
0$
#430
b10010 E
b10001 :
1D
1$
#440
0D
0$
#450
b10011 E
b10010 :
1D
1$
#460
0D
0$
#470
b10100 E
b10011 :
1D
1$
#480
0D
0$
#490
b10101 E
b10100 :
1D
1$
#500
0D
0$
#510
b10110 E
b10101 :
1D
1$
#520
0D
0$
#530
b10111 E
b10110 :
1D
1$
#540
0D
0$
#550
b11000 E
b10111 :
1D
1$
#560
0D
0$
#570
b11001 E
b11000 :
1D
1$
#580
0D
0$
#590
b11010 E
b11001 :
1D
1$
#600
0D
0$
#610
b0 !
b0 +
b11011 E
0/
b11010 :
1D
1$
#620
0D
0$
#630
b11100 E
b11011 :
1D
1$
#640
0D
0$
#650
b11101 E
b11100 :
1D
1$
#660
0D
0$
#670
b11110 E
b11101 :
1D
1$
#680
0D
0$
#690
b11111 E
b11110 :
1D
1$
#700
0D
0$
#710
b100000 E
b11111 :
1D
1$
#720
0D
0$
#730
b100001 E
b100000 :
1D
1$
#740
0D
0$
#750
b100010 E
b100001 :
1D
1$
#760
0D
0$
#770
b100011 E
b100010 :
1D
1$
#780
0D
0$
#790
b100100 E
b100011 :
1D
1$
#800
0D
0$
#810
b100101 E
b100100 :
1D
1$
#820
0D
0$
#830
b100110 E
b100101 :
1D
1$
#840
0D
0$
#850
b100111 E
b100110 :
1D
1$
#860
0D
0$
#870
b101000 E
b100111 :
1D
1$
#880
0D
0$
#890
b101001 E
b101000 :
1D
1$
#900
0D
0$
#910
b101010 E
b101001 :
1D
1$
#920
0D
0$
#930
b101011 E
b101010 :
1D
1$
#940
0D
0$
#950
b101100 E
b101011 :
1D
1$
#960
0D
0$
#970
b101101 E
b101100 :
1D
1$
#980
0D
0$
#990
b101110 E
b101101 :
1D
1$
#1000
0D
0$
#1010
b101111 E
b101110 :
1D
1$
#1020
0D
0$
#1030
b110000 E
b101111 :
1D
1$
#1040
0D
0$
#1050
b110001 E
b110000 :
1D
1$
#1060
0D
0$
#1070
b110010 E
b110001 :
1D
1$
#1080
0D
0$
#1090
b110011 E
b0 :
1D
1$
#1100
0D
0$
#1110
b110 !
b110 +
b110100 E
1/
b1 :
1D
1$
#1120
0D
0$
#1130
b110101 E
b10 :
1D
1$
#1140
0D
0$
#1150
b110110 E
b11 :
1D
1$
#1160
0D
0$
#1170
b110111 E
b100 :
1D
1$
#1180
0D
0$
#1190
b111000 E
b101 :
1D
1$
#1200
0D
0$
#1210
b111001 E
b110 :
1D
1$
#1220
0D
0$
#1230
b111010 E
b111 :
1D
1$
#1240
0D
0$
#1250
b111011 E
b1000 :
1D
1$
#1260
0D
0$
#1270
b111100 E
b1001 :
1D
1$
#1280
0D
0$
#1290
b111101 E
b1010 :
1D
1$
#1300
0D
0$
#1310
b111110 E
b1011 :
1D
1$
#1320
0D
0$
#1330
b111111 E
b1100 :
1D
1$
#1340
0D
0$
#1350
b1000000 E
b1101 :
1D
1$
#1360
0D
0$
#1370
b1000001 E
b1110 :
1D
1$
#1380
0D
0$
#1390
b1000010 E
b1111 :
1D
1$
#1400
0D
0$
#1410
b1000011 E
b10000 :
1D
1$
#1420
0D
0$
#1430
b1000100 E
b10001 :
1D
1$
#1440
0D
0$
#1450
b1000101 E
b10010 :
1D
1$
#1460
0D
0$
#1470
b1000110 E
b10011 :
1D
1$
#1480
0D
0$
#1490
b1000111 E
b10100 :
1D
1$
#1500
0D
0$
#1510
b1001000 E
b10101 :
1D
1$
#1520
0D
0$
#1530
b1001001 E
b10110 :
1D
1$
#1540
0D
0$
#1550
b1001010 E
b10111 :
1D
1$
#1560
0D
0$
#1570
b1001011 E
b11000 :
1D
1$
#1580
0D
0$
#1590
b1001100 E
b11001 :
1D
1$
#1600
0D
0$
#1610
b0 !
b0 +
b1001101 E
0/
b11010 :
1D
1$
#1620
0D
0$
#1630
b1001110 E
b11011 :
1D
1$
#1640
0D
0$
#1650
b1001111 E
b11100 :
1D
1$
#1660
0D
0$
#1670
b1010000 E
b11101 :
1D
1$
#1680
0D
0$
#1690
b1010001 E
b11110 :
1D
1$
#1700
0D
0$
#1710
b1010010 E
b11111 :
1D
1$
#1720
0D
0$
#1730
b1010011 E
b100000 :
1D
1$
#1740
0D
0$
#1750
b1010100 E
b100001 :
1D
1$
#1760
0D
0$
#1770
b1010101 E
b100010 :
1D
1$
#1780
0D
0$
#1790
b1010110 E
b100011 :
1D
1$
#1800
0D
0$
#1810
b1010111 E
b100100 :
1D
1$
#1820
0D
0$
#1830
b1011000 E
b100101 :
1D
1$
#1840
0D
0$
#1850
b1011001 E
b100110 :
1D
1$
#1860
0D
0$
#1870
b1011010 E
b100111 :
1D
1$
#1880
0D
0$
#1890
b1011011 E
b101000 :
1D
1$
#1900
0D
0$
#1910
b1011100 E
b101001 :
1D
1$
#1920
0D
0$
#1930
b1011101 E
b101010 :
1D
1$
#1940
0D
0$
#1950
b1011110 E
b101011 :
1D
1$
#1960
0D
0$
#1970
b1011111 E
b101100 :
1D
1$
#1980
0D
0$
#1990
b1100000 E
b101101 :
1D
1$
#2000
0D
0$
#2010
b1100001 E
b101110 :
1D
1$
#2020
0D
0$
#2030
b1100010 E
b101111 :
1D
1$
#2040
0D
0$
#2050
b1100011 E
b110000 :
1D
1$
#2060
0D
0$
#2070
b1100100 E
b110001 :
1D
1$
#2080
0D
0$
#2090
b1100101 E
b0 :
1D
1$
#2100
0D
0$
#2110
b110 !
b110 +
b1100110 E
1/
b1 :
1D
1$
#2120
0D
0$
#2130
b1100111 E
b10 :
1D
1$
#2140
0D
0$
#2150
b1101000 E
b11 :
1D
1$
#2160
0D
0$
#2170
b1101001 E
b100 :
1D
1$
#2180
0D
0$
#2190
b1101010 E
b101 :
1D
1$
#2200
0D
0$
#2210
b1101011 E
b110 :
1D
1$
#2220
0D
0$
#2230
b1101100 E
b111 :
1D
1$
#2240
0D
0$
#2250
b1101101 E
b1000 :
1D
1$
#2260
0D
0$
#2270
b1101110 E
b1001 :
1D
1$
#2280
0D
0$
#2290
b1101111 E
b1010 :
1D
1$
#2300
0D
0$
#2310
b1110000 E
b1011 :
1D
1$
#2320
0D
0$
#2330
b1110001 E
b1100 :
1D
1$
#2340
0D
0$
#2350
b1110010 E
b1101 :
1D
1$
#2360
0D
0$
#2370
b1110011 E
b1110 :
1D
1$
#2380
0D
0$
#2390
b1110100 E
b1111 :
1D
1$
#2400
0D
0$
#2410
b1110101 E
b10000 :
1D
1$
#2420
0D
0$
#2430
b1110110 E
b10001 :
1D
1$
#2440
0D
0$
#2450
b1110111 E
b10010 :
1D
1$
#2460
0D
0$
#2470
b1111000 E
b10011 :
1D
1$
#2480
0D
0$
#2490
b1111001 E
b10100 :
1D
1$
#2500
0D
0$
#2510
b1111010 E
b10101 :
1D
1$
#2520
0D
0$
#2530
b1111011 E
b10110 :
1D
1$
#2540
0D
0$
#2550
b1111100 E
b10111 :
1D
1$
#2560
0D
0$
#2570
b1111101 E
b11000 :
1D
1$
#2580
0D
0$
#2590
b1111110 E
b11001 :
1D
1$
#2600
0D
0$
#2610
b0 !
b0 +
b1111111 E
0/
b11010 :
1D
1$
#2620
0D
0$
#2630
b10000000 E
b11011 :
1D
1$
#2640
0D
0$
#2650
b10000001 E
b11100 :
1D
1$
#2660
0D
0$
#2670
b10000010 E
b11101 :
1D
1$
#2680
0D
0$
#2690
b10000011 E
b11110 :
1D
1$
#2700
0D
0$
#2710
b10000100 E
b11111 :
1D
1$
#2720
0D
0$
#2730
b10000101 E
b100000 :
1D
1$
#2740
0D
0$
#2750
b10000110 E
b100001 :
1D
1$
#2760
0D
0$
#2770
b10000111 E
b100010 :
1D
1$
#2780
0D
0$
#2790
b10001000 E
b100011 :
1D
1$
#2800
0D
0$
#2810
b10001001 E
b100100 :
1D
1$
#2820
0D
0$
#2830
b10001010 E
b100101 :
1D
1$
#2840
0D
0$
#2850
b10001011 E
b100110 :
1D
1$
#2860
0D
0$
#2870
b10001100 E
b100111 :
1D
1$
#2880
0D
0$
#2890
b10001101 E
b101000 :
1D
1$
#2900
0D
0$
#2910
b10001110 E
b101001 :
1D
1$
#2920
0D
0$
#2930
b10001111 E
b101010 :
1D
1$
#2940
0D
0$
#2950
b10010000 E
b101011 :
1D
1$
#2960
0D
0$
#2970
b10010001 E
b101100 :
1D
1$
#2980
0D
0$
#2990
b10010010 E
b101101 :
1D
1$
#3000
0D
0$
#3010
b10010011 E
b101110 :
1D
1$
#3020
0D
0$
#3030
b10010100 E
b101111 :
1D
1$
#3040
0D
0$
#3050
b10010101 E
b110000 :
1D
1$
#3060
0D
0$
#3070
b10010110 E
b110001 :
1D
1$
#3080
0D
0$
#3090
b10010111 E
b0 :
1D
1$
#3100
0D
0$
#3110
b110 !
b110 +
b10011000 E
1/
b1 :
1D
1$
#3120
0D
0$
#3130
b10011001 E
b10 :
1D
1$
#3140
0D
0$
#3150
b10011010 E
b11 :
1D
1$
#3160
0D
0$
#3170
b10011011 E
b100 :
1D
1$
#3180
0D
0$
#3190
b10011100 E
b101 :
1D
1$
#3200
0D
0$
#3210
b10011101 E
b110 :
1D
1$
#3220
0D
0$
#3230
b10011110 E
b111 :
1D
1$
#3240
0D
0$
#3250
b10011111 E
b1000 :
1D
1$
#3260
0D
0$
#3270
b10100000 E
b1001 :
1D
1$
#3280
0D
0$
#3290
b10100001 E
b1010 :
1D
1$
#3300
0D
0$
#3310
b10100010 E
b1011 :
1D
1$
#3320
0D
0$
#3330
b10100011 E
b1100 :
1D
1$
#3340
0D
0$
#3350
b10100100 E
b1101 :
1D
1$
#3360
0D
0$
#3370
b10100101 E
b1110 :
1D
1$
#3380
0D
0$
#3390
b10100110 E
b1111 :
1D
1$
#3400
0D
0$
#3410
b10100111 E
b10000 :
1D
1$
#3420
0D
0$
#3430
b10101000 E
b10001 :
1D
1$
#3440
0D
0$
#3450
b10101001 E
b10010 :
1D
1$
#3460
0D
0$
#3470
b10101010 E
b10011 :
1D
1$
#3480
0D
0$
#3490
b10101011 E
b10100 :
1D
1$
#3500
0D
0$
#3510
b10101100 E
b10101 :
1D
1$
#3520
0D
0$
#3530
b10101101 E
b10110 :
1D
1$
#3540
0D
0$
#3550
b10101110 E
b10111 :
1D
1$
#3560
0D
0$
#3570
b10101111 E
b11000 :
1D
1$
#3580
0D
0$
#3590
b10110000 E
b11001 :
1D
1$
#3600
0D
0$
#3610
b0 !
b0 +
b10110001 E
0/
b11010 :
1D
1$
#3620
0D
0$
#3630
b10110010 E
b11011 :
1D
1$
#3640
0D
0$
#3650
b10110011 E
b11100 :
1D
1$
#3660
0D
0$
#3670
b10110100 E
b11101 :
1D
1$
#3680
0D
0$
#3690
b10110101 E
b11110 :
1D
1$
#3700
0D
0$
#3710
b10110110 E
b11111 :
1D
1$
#3720
0D
0$
#3730
b10110111 E
b100000 :
1D
1$
#3740
0D
0$
#3750
b10111000 E
b100001 :
1D
1$
#3760
0D
0$
#3770
b10111001 E
b100010 :
1D
1$
#3780
0D
0$
#3790
b10111010 E
b100011 :
1D
1$
#3800
0D
0$
#3810
b10111011 E
b100100 :
1D
1$
#3820
0D
0$
#3830
b10111100 E
b100101 :
1D
1$
#3840
0D
0$
#3850
b10111101 E
b100110 :
1D
1$
#3860
0D
0$
#3870
b10111110 E
b100111 :
1D
1$
#3880
0D
0$
#3890
b10111111 E
b101000 :
1D
1$
#3900
0D
0$
#3910
b11000000 E
b101001 :
1D
1$
#3920
0D
0$
#3930
b11000001 E
b101010 :
1D
1$
#3940
0D
0$
#3950
b11000010 E
b101011 :
1D
1$
#3960
0D
0$
#3970
b11000011 E
b101100 :
1D
1$
#3980
0D
0$
#3990
b11000100 E
b101101 :
1D
1$
#4000
0D
0$
#4010
b11000101 E
b101110 :
1D
1$
#4020
0D
0$
#4030
b11000110 E
b101111 :
1D
1$
#4040
0D
0$
#4050
b11000111 E
b110000 :
1D
1$
#4060
0D
0$
#4070
b11001000 E
b110001 :
1D
1$
#4080
0D
0$
#4090
b11001001 E
b0 :
1D
1$
#4100
0D
0$
#4110
b110 !
b110 +
b11001010 E
1/
b1 :
1D
1$
#4120
0D
0$
#4130
b11001011 E
b10 :
1D
1$
#4140
0D
0$
#4150
b11001100 E
b11 :
1D
1$
#4160
0D
0$
#4170
b11001101 E
b100 :
1D
1$
#4180
0D
0$
#4190
b11001110 E
b101 :
1D
1$
#4200
0D
0$
#4210
b11001111 E
b110 :
1D
1$
#4220
0D
0$
#4230
b11010000 E
b111 :
1D
1$
#4240
0D
0$
#4250
b11010001 E
b1000 :
1D
1$
#4260
0D
0$
#4270
b11010010 E
b1001 :
1D
1$
#4280
0D
0$
#4290
b11010011 E
b1010 :
1D
1$
#4300
0D
0$
#4310
b11010100 E
b1011 :
1D
1$
#4320
0D
0$
#4330
b11010101 E
b1100 :
1D
1$
#4340
0D
0$
#4350
b11010110 E
b1101 :
1D
1$
#4360
0D
0$
#4370
b11010111 E
b1110 :
1D
1$
#4380
0D
0$
#4390
b11011000 E
b1111 :
1D
1$
#4400
0D
0$
#4410
b11011001 E
b10000 :
1D
1$
#4420
0D
0$
#4430
b11011010 E
b10001 :
1D
1$
#4440
0D
0$
#4450
b11011011 E
b10010 :
1D
1$
#4460
0D
0$
#4470
b11011100 E
b10011 :
1D
1$
#4480
0D
0$
#4490
b11011101 E
b10100 :
1D
1$
#4500
0D
0$
#4510
b11011110 E
b10101 :
1D
1$
#4520
0D
0$
#4530
b11011111 E
b10110 :
1D
1$
#4540
0D
0$
#4550
b11100000 E
b10111 :
1D
1$
#4560
0D
0$
#4570
b11100001 E
b11000 :
1D
1$
#4580
0D
0$
#4590
b11100010 E
b11001 :
1D
1$
#4600
0D
0$
#4610
b0 !
b0 +
b11100011 E
0/
b11010 :
1D
1$
#4620
0D
0$
#4630
b11100100 E
b11011 :
1D
1$
#4640
0D
0$
#4650
b11100101 E
b11100 :
1D
1$
#4660
0D
0$
#4670
b11100110 E
b11101 :
1D
1$
#4680
0D
0$
#4690
b11100111 E
b11110 :
1D
1$
#4700
0D
0$
#4710
b11101000 E
b11111 :
1D
1$
#4720
0D
0$
#4730
b11101001 E
b100000 :
1D
1$
#4740
0D
0$
#4750
b11101010 E
b100001 :
1D
1$
#4760
0D
0$
#4770
b11101011 E
b100010 :
1D
1$
#4780
0D
0$
#4790
b11101100 E
b100011 :
1D
1$
#4800
0D
0$
#4810
b11101101 E
b100100 :
1D
1$
#4820
0D
0$
#4830
b11101110 E
b100101 :
1D
1$
#4840
0D
0$
#4850
b11101111 E
b100110 :
1D
1$
#4860
0D
0$
#4870
b11110000 E
b100111 :
1D
1$
#4880
0D
0$
#4890
b11110001 E
b101000 :
1D
1$
#4900
0D
0$
#4910
b11110010 E
b101001 :
1D
1$
#4920
0D
0$
#4930
b11110011 E
b101010 :
1D
1$
#4940
0D
0$
#4950
b11110100 E
b101011 :
1D
1$
#4960
0D
0$
#4970
b11110101 E
b101100 :
1D
1$
#4980
0D
0$
#4990
b11110110 E
b101101 :
1D
1$
#5000
0D
0$
#5010
b11110111 E
b101110 :
1D
1$
#5020
0D
0$
#5030
b11111000 E
b101111 :
1D
1$
#5040
0D
0$
#5050
b11111001 E
b110000 :
1D
1$
#5060
0D
0$
#5070
b11111010 E
b110001 :
1D
1$
#5080
0D
0$
#5090
b11111011 E
b0 :
1D
1$
#5100
0D
0$
#5110
b110 !
b110 +
b11111100 E
1/
b1 :
1D
1$
#5120
0D
0$
#5130
b11111101 E
b10 :
1D
1$
#5140
0D
0$
#5150
b11111110 E
b11 :
1D
1$
#5160
0D
0$
#5170
b11111111 E
b100 :
1D
1$
#5180
0D
0$
#5190
b100000000 E
b101 :
1D
1$
#5200
0D
0$
#5210
b100000001 E
b110 :
1D
1$
#5220
0D
0$
#5230
b100000010 E
b111 :
1D
1$
#5240
0D
0$
#5250
b100000011 E
b1000 :
1D
1$
#5260
0D
0$
#5270
b100000100 E
b1001 :
1D
1$
#5280
0D
0$
#5290
b100000101 E
b1010 :
1D
1$
#5300
0D
0$
#5310
b100000110 E
b1011 :
1D
1$
#5320
0D
0$
#5330
b100000111 E
b1100 :
1D
1$
#5340
0D
0$
#5350
b100001000 E
b1101 :
1D
1$
#5360
0D
0$
#5370
b100001001 E
b1110 :
1D
1$
#5380
0D
0$
#5390
b100001010 E
b1111 :
1D
1$
#5400
0D
0$
#5410
b100001011 E
b10000 :
1D
1$
#5420
0D
0$
#5430
b100001100 E
b10001 :
1D
1$
#5440
0D
0$
#5450
b100001101 E
b10010 :
1D
1$
#5460
0D
0$
#5470
b100001110 E
b10011 :
1D
1$
#5480
0D
0$
#5490
b100001111 E
b10100 :
1D
1$
#5500
0D
0$
#5510
b100010000 E
b10101 :
1D
1$
#5520
0D
0$
#5530
b100010001 E
b10110 :
1D
1$
#5540
0D
0$
#5550
b100010010 E
b10111 :
1D
1$
#5560
0D
0$
#5570
b100010011 E
b11000 :
1D
1$
#5580
0D
0$
#5590
b100010100 E
b11001 :
1D
1$
#5600
0D
0$
#5610
b0 !
b0 +
b100010101 E
0/
b11010 :
1D
1$
#5620
0D
0$
#5630
b100010110 E
b11011 :
1D
1$
#5640
0D
0$
#5650
b100010111 E
b11100 :
1D
1$
#5660
0D
0$
#5670
b100011000 E
b11101 :
1D
1$
#5680
0D
0$
#5690
b100011001 E
b11110 :
1D
1$
#5700
0D
0$
#5710
b100011010 E
b11111 :
1D
1$
#5720
0D
0$
#5730
b100011011 E
b100000 :
1D
1$
#5740
0D
0$
